ps_proxy/__init__.py
ps_proxy/proxy.py
ps_proxy/database/crud.py
ps_proxy/database/tables.py
ps_proxy/request/__init__.py
ps_proxy/request/get.py
ps_proxy/request/pp1.py
ps_proxy/request/pp2.py
ps_proxy/request/pp3.py
ps_proxy/request/pp4.py
ps_proxy/request/proxy_data.py
ps_proxy-0.1.4.dist-info/licenses/LICENSE
ps_proxy-0.1.4.dist-info/METADATA
ps_proxy-0.1.4.dist-info/WHEEL
ps_proxy-0.1.4.dist-info/top_level.txt
ps_proxy-0.1.4.dist-info/RECORD
